<?xml version="1.0"?>

<root available-locales="en_US" default-locale="en_US">
	<dynamic-element instance-id="O7cO9c99" name="effectIn" type="option" index-type="">
		<dynamic-content><![CDATA[fadeIn]]></dynamic-content>
	</dynamic-element>

	<dynamic-element instance-id="O7cO9c98" name="showOnEvent" type="option" index-type="">
		<dynamic-content><![CDATA[screen]]></dynamic-content>
	</dynamic-element>

	<dynamic-element instance-id="O7cO9c97" name="animationTime" type="option" index-type="">
		<dynamic-content><![CDATA[1s]]></dynamic-content>
	</dynamic-element>

	<dynamic-element instance-id="O7cO9c96" name="contentCentered" type="option" index-type="">
		<dynamic-content><![CDATA[yes]]></dynamic-content>
	</dynamic-element>

	<dynamic-element instance-id="O7cO9c95" name="backgroundImage" type="document_library" index-type="">
		<dynamic-content><![CDATA[[$FILE=Malaysia_01.jpg$]]]></dynamic-content>
	</dynamic-element>

	<dynamic-element instance-id="O7cO9c93" name="backgroundColor" type="option" index-type="">
		<dynamic-content><![CDATA[#543623]]></dynamic-content>
	</dynamic-element>

	<dynamic-element instance-id="O7cO9c94" name="content" type="ddm-text-html" index-type="">
		<dynamic-content><![CDATA[<div style="color:#FFF; text-shadow: 1px 0px 2px rgba(150, 150, 150, 1);" class="text-center">
			<h1 style="font-size:50px">DISCOVER THE BEAUTY OF MALAYSIA</h1>
			<h2>There's always something happening around Malaysia</h2>
			<a href="malaysia" class="btn btn-success btn-large">Go to Malaysia page</a>
		</div>]]></dynamic-content>
	</dynamic-element>
</root>